{
    "peterj@icloud.com": {
        "password": "hello!",
        "avatar": "..\/images\/youngman_2.png",
        "username": "peterj"
    },
    "ada@gmail.com": {
        "password": "ada123",
        "avatar": "..\/images\/woman_2.png",
        "username": "ada"
    },
    "david@hotmail.com": {
        "password": "DDDD2010",
        "avatar": "..\/images\/boy_2.png",
        "username": "david"
    },
    "lucy@163.com": {
        "password": "6flyingcats",
        "avatar": "..\/images\/girl_3.png",
        "username": "lucy"
    },
    "zebrafish@outlook.com": {
        "password": "GloFish",
        "avatar": "..\/images\/oldman_1.png",
        "username": "zebrafish"
    },
    "emma@smith.edu": {
        "password": "emmaishere",
        "avatar": "..\/images\/youngwoman_2.png",
        "username": "emma"
    },
    "yyin@smith.edu": {
        "password": "yyin",
        "avatar": "..\/images\/youngwoman_2.png",
        "username": "yyin"
    },
    "llyu69@smith.edu": {
        "password": "1234!",
        "avatar": "..\/images\/oldman_1.png",
        "username": "llyu69"
    },
    "betty@icloud.com": {
        "password": "betty",
        "avatar": "..\/images\/youngwoman_3.png",
        "username": "betty"
    },
    "husguew@smith.edu": {
        "password": "hahahahahahahahahaha",
        "avatar": "..\/images\/oldman_1.png",
        "username": "husguew"
    },
    "oldMAN@smith.no": {
        "password": "hahahahahah",
        "avatar": "..\/images\/youngman_3.png",
        "username": "oldMAN"
    }
}